sitepath/__init__.py
sitepath/__main__.py
sitepath/_version.py
sitepath/common.py
sitepath/core.py
sitepath/crumb.py
sitepath/ops.py
sitepath-0.4.0.dist-info/LICENSE.txt
sitepath-0.4.0.dist-info/METADATA
sitepath-0.4.0.dist-info/WHEEL
sitepath-0.4.0.dist-info/top_level.txt
sitepath-0.4.0.dist-info/RECORD
