Metadata-Version: 2.1
Name: sitepath
Version: 0.4.0
Summary: the anti-packaging system
Home-page: https://github.com/serwy/sitepath
Author: Roger D. Serwy
Author-email: roger.serwy@gmail.com
License: Apache v2.0
Classifier: Topic :: Software Development :: Libraries
Classifier: Topic :: Utilities
Classifier: Development Status :: 4 - Beta
Classifier: Operating System :: OS Independent
Classifier: Programming Language :: Python :: 3.6
Classifier: License :: OSI Approved :: Apache Software License
License-File: LICENSE.txt
